odoo10_addon_l10n_nl_dutch_company_type-10.0.1.0.0-py2.7-nspkg.pth
odoo/addons/l10n_nl_dutch_company_type/README.rst
odoo/addons/l10n_nl_dutch_company_type/__init__.py
odoo/addons/l10n_nl_dutch_company_type/__manifest__.py
odoo/addons/l10n_nl_dutch_company_type/data/l10n_nl_dutch_company_type.xml
odoo/addons/l10n_nl_dutch_company_type/i18n/nl.po
odoo/addons/l10n_nl_dutch_company_type/static/description/icon.png
odoo10_addon_l10n_nl_dutch_company_type-10.0.1.0.0.dist-info/DESCRIPTION.rst
odoo10_addon_l10n_nl_dutch_company_type-10.0.1.0.0.dist-info/METADATA
odoo10_addon_l10n_nl_dutch_company_type-10.0.1.0.0.dist-info/RECORD
odoo10_addon_l10n_nl_dutch_company_type-10.0.1.0.0.dist-info/WHEEL
odoo10_addon_l10n_nl_dutch_company_type-10.0.1.0.0.dist-info/metadata.json
odoo10_addon_l10n_nl_dutch_company_type-10.0.1.0.0.dist-info/namespace_packages.txt
odoo10_addon_l10n_nl_dutch_company_type-10.0.1.0.0.dist-info/top_level.txt
